{
    "folder": "165",
    "files": {
        "341": {
            "type": ".jpg"
        },
        "358": {
            "type": ".jpg"
        },
        "360": {
            "type": ".jpg"
        },
        "362": {
            "type": ".jpg"
        },
        "363": {
            "type": ".jpg"
        },
        "370": {
            "type": ".jpg"
        },
        "371": {
            "type": ".jpg"
        },
        "372": {
            "type": ".jpg"
        },
        "373": {
            "type": ".jpg"
        },
        "374": {
            "type": ".jpg"
        },
        "375": {
            "type": ".jpg"
        },
        "376": {
            "type": ".jpg"
        },
        "377": {
            "type": ".jpg"
        },
        "378": {
            "type": ".jpg"
        },
        "379": {
            "type": ".jpg"
        }
    }
}
